ai_api/__init__.py
ai_api/api/__init__.py
ai_api/api/default_api.py
ai_api/api_client.py
ai_api/api_response.py
ai_api/configuration.py
ai_api/exceptions.py
ai_api/models/__init__.py
ai_api/models/client_id.py
ai_api/models/client_secret.py
ai_api/models/cluster_in.py
ai_api/models/cluster_out.py
ai_api/models/finished_at.py
ai_api/models/grant_type.py
ai_api/models/http_validation_error.py
ai_api/models/id.py
ai_api/models/id_out.py
ai_api/models/job_instance_in.py
ai_api/models/job_instance_out.py
ai_api/models/log_out.py
ai_api/models/provider.py
ai_api/models/provider_in.py
ai_api/models/provider_out.py
ai_api/models/provider_type_out.py
ai_api/models/repository_in.py
ai_api/models/repository_out.py
ai_api/models/ssh_key_in.py
ai_api/models/ssh_key_out.py
ai_api/models/validation_error.py
ai_api/models/validation_error_loc_inner.py
ai_api/py.typed
ai_api/rest.py
codedepot_ai_api-1.1.2.dist-info/METADATA
codedepot_ai_api-1.1.2.dist-info/WHEEL
test/__init__.py
test/test_client_id.py
test/test_client_secret.py
test/test_cluster_in.py
test/test_cluster_out.py
test/test_default_api.py
test/test_finished_at.py
test/test_grant_type.py
test/test_http_validation_error.py
test/test_id.py
test/test_id_out.py
test/test_job_instance_in.py
test/test_job_instance_out.py
test/test_log_out.py
test/test_provider.py
test/test_provider_in.py
test/test_provider_out.py
test/test_provider_type_out.py
test/test_repository_in.py
test/test_repository_out.py
test/test_ssh_key_in.py
test/test_ssh_key_out.py
test/test_validation_error.py
test/test_validation_error_loc_inner.py
codedepot_ai_api-1.1.2.dist-info/RECORD
