Metadata-Version: 2.1
Name: codedepot-ai-api
Version: 1.1.2
Summary: AI API
Keywords: OpenAPI,OpenAPI-Generator,FastAPI
Author-Email: OpenAPI Generator Community <team@openapitools.org>, CodeDepot <contact@codedepot.ai>
License: NoLicense
Project-URL: Repository, https://github.com/GIT_USER_ID/GIT_REPO_ID
Project-URL: Homepage, https://codedepot.ai
Requires-Python: <4.0,>=3.7
Requires-Dist: urllib3>=1.25.3
Requires-Dist: python-dateutil>=2.8.2
Requires-Dist: pydantic>=2
Requires-Dist: typing-extensions>=4.7.1
Requires-Dist: pydantic>=2
Requires-Dist: python-dateutil
Requires-Dist: typing-extensions>=4.7.1
Requires-Dist: urllib3<2.1.0,>=1.25.3
